sql_database_zoutigewolf/__init__.py
sql_database_zoutigewolf/database.py
sql_database_zoutigewolf-1.0.6.dist-info/LICENSE
sql_database_zoutigewolf-1.0.6.dist-info/METADATA
sql_database_zoutigewolf-1.0.6.dist-info/WHEEL
sql_database_zoutigewolf-1.0.6.dist-info/top_level.txt
sql_database_zoutigewolf-1.0.6.dist-info/RECORD
