Metadata-Version: 2.1
Name: sql-database-zoutigewolf
Version: 1.0.6
Summary: pymysql wrapper
Author-email: ZoutigeWolf <guuskamphuis@gmail.com>
Classifier: Programming Language :: Python :: 3
Classifier: License :: OSI Approved :: MIT License
Classifier: Operating System :: OS Independent
Requires-Python: >=3.10
License-File: LICENSE
Requires-Dist: PyMySQL
